diversity/__init__.py
diversity/compression.py
diversity/embedding.py
diversity/functions.py
diversity/homogenization.py
diversity/ngram_diversity.py
diversity/patterns/Token.py
diversity/patterns/__init__.py
diversity/patterns/part_of_speech.py
diversity/qudsim.py
diversity/qudsim_modules/__init__.py
diversity/qudsim_modules/qudsim_alignment/align.py
diversity/qudsim_modules/qudsim_alignment/answer.py
diversity/qudsim_modules/qudsim_alignment/metric.py
diversity/qudsim_modules/qudsim_alignment/similarity.py
diversity/qudsim_modules/qudsim_preprocessing/number.py
diversity/qudsim_modules/qudsim_qud_generation/decontextualize.py
diversity/qudsim_modules/qudsim_qud_generation/pipeline.py
diversity/qudsim_modules/qudsim_qud_generation/qud.py
diversity/qudsim_modules/qudsim_qud_generation/segment.py
diversity/self_repetition.py
diversity/template.py
diversity/utils/__init__.py
diversity/utils/memoize.py
diversity/utils/openai.py
diversity-0.3.0.dist-info/LICENSE.md
diversity-0.3.0.dist-info/METADATA
diversity-0.3.0.dist-info/WHEEL
diversity-0.3.0.dist-info/RECORD
