Metadata-Version: 2.3
Name: diversity
Version: 0.3.0
Summary: 
Author: Chantal Shaib
Author-email: shaib.c@northeastern.edu
Requires-Python: >=3.10,<3.13
Classifier: Programming Language :: Python :: 3
Classifier: Programming Language :: Python :: 3.10
Classifier: Programming Language :: Python :: 3.11
Classifier: Programming Language :: Python :: 3.12
Requires-Dist: evaluate (>=0.4.1,<0.5.0)
Requires-Dist: nltk (>=3.8.1,<4.0.0)
Requires-Dist: rouge-score (>=0.1.2,<0.2.0)
Requires-Dist: sentence-transformers (>=5.1.0,<6.0.0)
Requires-Dist: transformers (>=4.41.0,<5.0.0)
Requires-Dist: typer (>=0.9.0)
